
{"timestamp": "2023-08-01T11:59:36Z", "repository": "gabeungureanu/webflow2", "pusher": "gabeungureanu", "commit_hash": "d396cccddb828dc1f1c23988e3345314d10ff048", "commit_message": "Update EmailNotifications.yml"}
{"timestamp": "2023-08-01T12:10:15Z", "repository": "gabeungureanu/webflow2", "pusher": "gabeungureanu", "commit_hash": "2e041e606d660b5731fe7998ea021ce2339c57d9", "commit_message": "Update EmailNotifications.yml"}
{"timestamp": "2023-08-01T12:11:14Z", "repository": "gabeungureanu/webflow2", "pusher": "gabeungureanu", "commit_hash": "d47efc7e470d8772cf01d8fe182d20c1661b4129", "commit_message": "Update EmailNotifications.yml"},
